test_5_dec/__init__.py
test_5_dec/_modidx.py
test_5_dec/core.py
test_5_dec-0.0.1.dist-info/licenses/LICENSE
test_5_dec-0.0.1.dist-info/METADATA
test_5_dec-0.0.1.dist-info/WHEEL
test_5_dec-0.0.1.dist-info/entry_points.txt
test_5_dec-0.0.1.dist-info/top_level.txt
test_5_dec-0.0.1.dist-info/RECORD
